django_json_tag-0.0.1.dist-info/DESCRIPTION.rst
django_json_tag-0.0.1.dist-info/METADATA
django_json_tag-0.0.1.dist-info/RECORD
django_json_tag-0.0.1.dist-info/WHEEL
django_json_tag-0.0.1.dist-info/metadata.json
django_json_tag-0.0.1.dist-info/top_level.txt
json_tag/__init__.py
json_tag/dumper.py
json_tag/http.py
json_tag/models.py
json_tag/serializers.py
json_tag/testutils.py
json_tag/views.py
json_tag/templatetags/__init__.py
json_tag/templatetags/json_tag/__init__.py
json_tag/templatetags/json_tag/filters.py
json_tag/templatetags/json_tag/library.py
json_tag/templatetags/json_tag/tags.py
