Metadata-Version: 1.2
Name: django-json-tag
Version: 0.0.1
Summary: A lightweight collection of JSON helpers for Django.
Home-page: https://github.com/graingert/django-json-tag
Author: fusionbox, inc.
Author-email: programmers@fusionbox.com
Maintainer: Thomas Grainger
Maintainer-email: django-json-tag@graingert.co.uk
License: UNKNOWN
Keywords: rest json views django helpers
Platform: UNKNOWN
Classifier: Development Status :: 5 - Production/Stable
Classifier: Framework :: Django
Classifier: Intended Audience :: Developers
Classifier: License :: OSI Approved :: BSD License
Classifier: Topic :: Internet :: WWW/HTTP
Classifier: Topic :: Software Development :: Libraries
Classifier: Programming Language :: Python
Classifier: Programming Language :: Python :: 2.7
Classifier: Programming Language :: Python :: 3.4
Classifier: Programming Language :: Python :: 3.5
Classifier: Programming Language :: Python :: 3.6
